LICENSE
README.md
setup.py
callibri_ecg/callibri_ecg_lib.py
callibri_ecg/sample.py
callibri_ecg/libs/macos/libCallibriUtils.dylib
callibri_ecg/libs/win/callibri_utils-x64.dll
callibri_ecg/libs/win/callibri_utils-x86.dll
pycallibri_ecg.egg-info/PKG-INFO
pycallibri_ecg.egg-info/SOURCES.txt
pycallibri_ecg.egg-info/dependency_links.txt
pycallibri_ecg.egg-info/top_level.txt