Metadata-Version: 2.1
Name: pycallibri_ecg
Version: 1.0.2
Summary: Python wrapper for CallibriECG library
Home-page: https://gitlab.com/neurosdk2/neurosamples/-/tree/main/python
Author: Brainbit Inc.
Author-email: support@brainbit.com
License: MIT
Classifier: Programming Language :: Python :: 3
Classifier: License :: OSI Approved :: MIT License
Classifier: Operating System :: Microsoft :: Windows
Classifier: Operating System :: MacOS
Classifier: Intended Audience :: Developers
Requires-Python: >=3.7
License-File: LICENSE
